setup.py
configuration_example/jupyter_jupyterlab_telemetry_producer_demo_config.py
configuration_example/jupyter_jupyterlab_telemetry_router_config.py
jupyterlab-telemetry-producer-demo/__init__.py
jupyterlab-telemetry-producer-demo/_version.py
jupyterlab-telemetry-producer-demo/application.py
jupyterlab-telemetry-producer-demo/handlers.py
jupyterlab_telemetry_producer_demo-0.1.4.data/data/etc/jupyter/jupyter_server_config.d/jupyterlab-telemetry-producer-demo.json
jupyterlab_telemetry_producer_demo-0.1.4.data/data/share/jupyter/labextensions/jupyterlab-telemetry-producer-demo/package.json
jupyterlab_telemetry_producer_demo-0.1.4.data/data/share/jupyter/labextensions/jupyterlab-telemetry-producer-demo/static/630.0064a083e63690ec6b37.js
jupyterlab_telemetry_producer_demo-0.1.4.data/data/share/jupyter/labextensions/jupyterlab-telemetry-producer-demo/static/743.74e763b63e0ffd199d5e.js
jupyterlab_telemetry_producer_demo-0.1.4.data/data/share/jupyter/labextensions/jupyterlab-telemetry-producer-demo/static/747.0648166a4cdbe8ed9626.js
jupyterlab_telemetry_producer_demo-0.1.4.data/data/share/jupyter/labextensions/jupyterlab-telemetry-producer-demo/static/763.634eabf720e639ee193e.js
jupyterlab_telemetry_producer_demo-0.1.4.data/data/share/jupyter/labextensions/jupyterlab-telemetry-producer-demo/static/remoteEntry.3d1d9195a4884c98d243.js
jupyterlab_telemetry_producer_demo-0.1.4.data/data/share/jupyter/labextensions/jupyterlab-telemetry-producer-demo/static/style.js
jupyterlab_telemetry_producer_demo-0.1.4.data/data/share/jupyter/labextensions/jupyterlab-telemetry-producer-demo/static/third-party-licenses.json
jupyterlab_telemetry_producer_demo-0.1.4.data/data/share/jupyter/labextensions/jupyterlab-telemetry-producer-demo/install.json
jupyterlab_telemetry_producer_demo-0.1.4.dist-info/METADATA
jupyterlab_telemetry_producer_demo-0.1.4.dist-info/WHEEL
jupyterlab_telemetry_producer_demo-0.1.4.dist-info/licenses/LICENSE
jupyterlab_telemetry_producer_demo-0.1.4.dist-info/RECORD
